hcp2bids/__init__.py
hcp2bids/convert.py
hcp2bids/download.py
hcp2bids/subjects/HCP_1200.txt
hcp2bids/subjects/HCP_1200_exclude.txt
hcp2bids/subjects/HCP_Retest.txt
hcp2bids/subjects/__init__.py
hcp2bids-0.2.0.dist-info/LICENSE
hcp2bids-0.2.0.dist-info/WHEEL
hcp2bids-0.2.0.dist-info/METADATA
hcp2bids-0.2.0.dist-info/RECORD
