Metadata-Version: 2.1
Name: hcp2bids
Version: 0.2.0
Summary: For downloading and converting HCP1200 data into BIDS spec.
License: MIT
Author: j1c
Author-email: jaewonc78@gmail.com
Requires-Python: >=3.6,<4.0
Classifier: License :: OSI Approved :: MIT License
Classifier: Programming Language :: Python :: 3
Classifier: Programming Language :: Python :: 3.6
Classifier: Programming Language :: Python :: 3.7
Classifier: Programming Language :: Python :: 3.8
Classifier: Programming Language :: Python :: 3.9
Requires-Dist: boto3 (>=1.15.1,<2.0.0)
Requires-Dist: pybids (>=0.9.3)
